{
  "db_name": "PostgreSQL",
  "query": "SELECT\n    id,\n    name,\n    mail\nFROM\n    passkey_users\nWHERE\n    mail = $1;\n",
  "describe": {
    "columns": [
      {
        "ordinal": 0,
        "name": "id",
        "type_info": "Uuid"
      },
      {
        "ordinal": 1,
        "name": "name",
        "type_info": "Text"
      },
      {
        "ordinal": 2,
        "name": "mail",
        "type_info": "Text"
      }
    ],
    "parameters": {
      "Left": [
        "Text"
      ]
    },
    "nullable": [
      false,
      false,
      false
    ]
  },
  "hash": "9f1f65ad6a2e6dda5049ae4212b11ec2d41d313f397fdda141212a681ca0494e"
}
